proompter/__init__.py
proompter/proompter.py
proompter/setup.py
proompter-0.0.2.dist-info/LICENSE
proompter-0.0.2.dist-info/METADATA
proompter-0.0.2.dist-info/WHEEL
proompter-0.0.2.dist-info/top_level.txt
proompter-0.0.2.dist-info/RECORD
