Metadata-Version: 2.1
Name: proompter
Version: 0.0.2
Summary: Simple wrapper around some Llm handlers.
Author: Kyrylo Mordan
Author-email: parachute.repo@gmail.com
Classifier: Development Status :: 3 - Alpha
Classifier: Intended Audience :: Developers
Classifier: Intended Audience :: Science/Research
Classifier: Programming Language :: Python :: 3
Classifier: Programming Language :: Python :: 3.9
Classifier: Programming Language :: Python :: 3.10
Classifier: Programming Language :: Python :: 3.11
Classifier: License :: OSI Approved :: MIT License
Classifier: Topic :: Scientific/Engineering
License-File: LICENSE
Requires-Dist: ollama==0.2.1
Requires-Dist: huggingface-hub==0.24.2
Requires-Dist: transformers==4.43.2
Requires-Dist: pandas==2.1.1
Requires-Dist: mocker-db==0.2.0
Requires-Dist: attrs==23.2.0
